sitka/__init__.py
sitka/calculations/__init__.py
sitka/calculations/conduction.py
sitka/calculations/convection.py
sitka/calculations/fluids.py
sitka/calculations/radiation.py
sitka/calculations/solar.py
sitka/calculations/tests/__init__.py
sitka/calculations/tests/test_calculations.py
sitka/calculations/tests/test_external_shortwave_radiation.py
sitka/calculations/tests/test_surface_solar_angles.py
sitka/components/__init__.py
sitka/components/site.py
sitka/components/surface.py
sitka/components/tests/__init__.py
sitka/components/tests/test_site.py
sitka/components/tests/test_surface.py
sitka/general/__init__.py
sitka/general/settings.py
sitka/general/tests/__init__.py
sitka/general/tests/test_settings.py
sitka/io/__init__.py
sitka/io/time.py
sitka/io/weather.py
sitka/io/tests/__init__.py
sitka/io/tests/test_time.py
sitka/io/tests/test_weather.py
sitka/utils/__init__.py
sitka/utils/time_series.py
sitka-0.1.4.dist-info/LICENSE
sitka-0.1.4.dist-info/METADATA
sitka-0.1.4.dist-info/WHEEL
sitka-0.1.4.dist-info/top_level.txt
sitka-0.1.4.dist-info/RECORD
