Metadata-Version: 2.1
Name: sitka
Version: 0.1.4
Summary: A built environment analysis and modeling library for Python.
Home-page: https://github.com/mcneillj/sitka
Author: James McNeill
License: UNKNOWN
Keywords: simulation setuptools development
Platform: UNKNOWN
Classifier: Development Status :: 3 - Alpha
Classifier: Environment :: Console
Classifier: Intended Audience :: Science/Research
Classifier: Topic :: Scientific/Engineering
Classifier: License :: OSI Approved :: MIT License
Classifier: Programming Language :: Python :: 3.6
Classifier: Programming Language :: Python :: 3.7
Classifier: Programming Language :: Python :: 3.8
Requires-Dist: numpy (>=1.19.2)
Requires-Dist: pandas (>=1.1.2)
Requires-Dist: pytest (>=6.0.2)
